ems_config/__init__.py
ems_config/config.py
ems_config/helpers.py
ems_config/vars.py
ems_config-0.0.15.dist-info/METADATA
ems_config-0.0.15.dist-info/WHEEL
ems_config-0.0.15.dist-info/top_level.txt
ems_config-0.0.15.dist-info/RECORD
