Metadata-Version: 2.1
Name: ems-config
Version: 0.0.15
Summary: Common configuration utilities for EMS projects
Home-page: https://gitlab.com/thedirtyfew/utilities/ems-config
Author: Emil Haldrup Eriksen
Author-email: emil.h.eriksen@gmail.com
License: MIT
Platform: UNKNOWN
Requires-Python: >=3
Requires-Dist: requests
Requires-Dist: pyyaml
Requires-Dist: pytz
